CHANGES.txt
COPYRIGHT.txt
LICENSE.txt
README.txt
bootstrap.py
buildout.cfg
setup.py
src/zope/__init__.py
src/zope.app.zopeappgenerations.egg-info/PKG-INFO
src/zope.app.zopeappgenerations.egg-info/SOURCES.txt
src/zope.app.zopeappgenerations.egg-info/dependency_links.txt
src/zope.app.zopeappgenerations.egg-info/namespace_packages.txt
src/zope.app.zopeappgenerations.egg-info/not-zip-safe
src/zope.app.zopeappgenerations.egg-info/requires.txt
src/zope.app.zopeappgenerations.egg-info/top_level.txt
src/zope/app/__init__.py
src/zope/app/zopeappgenerations/__init__.py
src/zope/app/zopeappgenerations/configure.zcml
src/zope/app/zopeappgenerations/evolve2.py
src/zope/app/zopeappgenerations/evolve3.py
src/zope/app/zopeappgenerations/evolve4.py
src/zope/app/zopeappgenerations/evolve5.py