Metadata-Version: 1.0
Name: zope.app.zopeappgenerations
Version: 3.6.1
Summary: Zope Application ZODB Update Generations
Home-page: http://pypi.python.org/pypi/zope.app.zopeappgenerations
Author: Zope Foundation and Contributors
Author-email: zope-dev@zope.org
License: ZPL 2.1
Keywords: zope3 zodb generation update
Platform: UNKNOWN
Classifier: Development Status :: 5 - Production/Stable
Classifier: Environment :: Web Environment
Classifier: Intended Audience :: Developers
Classifier: License :: OSI Approved :: Zope Public License
Classifier: Programming Language :: Python
Classifier: Natural Language :: English
Classifier: Operating System :: OS Independent
Classifier: Topic :: Internet :: WWW/HTTP
Classifier: Framework :: Zope3
